MANIFEST.in
setup.py
docs/HISTORY.txt
src/megrok/__init__.py
src/megrok.pagetemplate.egg-info/PKG-INFO
src/megrok.pagetemplate.egg-info/SOURCES.txt
src/megrok.pagetemplate.egg-info/dependency_links.txt
src/megrok.pagetemplate.egg-info/entry_points.txt
src/megrok.pagetemplate.egg-info/namespace_packages.txt
src/megrok.pagetemplate.egg-info/not-zip-safe
src/megrok.pagetemplate.egg-info/requires.txt
src/megrok.pagetemplate.egg-info/top_level.txt
src/megrok/pagetemplate/README.txt
src/megrok/pagetemplate/__init__.py
src/megrok/pagetemplate/components.py
src/megrok/pagetemplate/meta.py
src/megrok/pagetemplate/meta.zcml
src/megrok/pagetemplate/utils.py
src/megrok/pagetemplate/tests/__init__.py
src/megrok/pagetemplate/tests/ftesting.zcml
src/megrok/pagetemplate/tests/namedtemplates.py
src/megrok/pagetemplate/tests/notemplate.py
src/megrok/pagetemplate/tests/registration.py
src/megrok/pagetemplate/tests/test_package.py
src/megrok/pagetemplate/tests/templates/test.pt