Metadata-Version: 1.0
Name: megrok.pagetemplate
Version: 0.5
Summary: Page template component for Grok, based on zope.pagetemplate
Home-page: http://pypi.python.org/pypi/megrok.pagetemplate
Author: Souheil Chelfouh
Author-email: trollfot@gmail.com
License: GPL
Keywords: Grok Pagetemplate Zope Layout Dolmen
Platform: Any
Classifier: Development Status :: 4 - Beta
Classifier: Environment :: Web Environment
Classifier: Framework :: Zope3
Classifier: Intended Audience :: Other Audience
Classifier: License :: OSI Approved :: GNU General Public License (GPL)
Classifier: Operating System :: OS Independent
Classifier: Programming Language :: Python
